spatialOmics/__init__.py
spatialOmics/spatialOmics.py
spatialOmics/utils.py
ai4scr_spatial_omics-0.1.1.dist-info/METADATA
ai4scr_spatial_omics-0.1.1.dist-info/WHEEL
ai4scr_spatial_omics-0.1.1.dist-info/top_level.txt
ai4scr_spatial_omics-0.1.1.dist-info/RECORD
