Metadata-Version: 2.1
Name: ai4scr-spatial-omics
Version: 0.1.1
Summary: Installable spatialOmics package
Home-page: https://github.com/AI4SCR/spatial-omics
Author: Adriano Martinelli
Author-email: art@zurich.ibm.com
Requires-Dist: numpy (>=1.22)
Requires-Dist: pandas (>=1.2)
Requires-Dist: scikit-image (>=0.19.2)
Requires-Dist: seaborn (>=0.11.2)
Requires-Dist: tqdm (>=4.64.0)
Requires-Dist: h5py (>=3.6.0)
Requires-Dist: tables (>=3.7.0)
Requires-Dist: scikit-learn (>=1.0.2)
Provides-Extra: dev
Requires-Dist: pytest ; extra == 'dev'
Requires-Dist: pytest-cov ; extra == 'dev'
Requires-Dist: black (==21.5b0) ; extra == 'dev'
Requires-Dist: flake8 ; extra == 'dev'
Requires-Dist: mypy ; extra == 'dev'
Requires-Dist: sphinx ; extra == 'dev'
Requires-Dist: sphinx-autodoc-typehints ; extra == 'dev'
Requires-Dist: better-apidoc ; extra == 'dev'
Requires-Dist: six ; extra == 'dev'
Requires-Dist: sphinx-rtd-theme ; extra == 'dev'
Requires-Dist: myst-parser ; extra == 'dev'
Provides-Extra: test
Requires-Dist: pytest ; extra == 'test'
Requires-Dist: pytest-cov ; extra == 'test'
Provides-Extra: vcs
